empulse/_types.py
empulse/__init__.py
empulse/py.typed
empulse/metrics/max_profit.py
empulse/metrics/lift.py
empulse/metrics/_convex_hull.py
empulse/metrics/__init__.py
empulse/metrics/savings.py
empulse/metrics/common.py
empulse/metrics/_validation.py
empulse/metrics/credit_scoring/deterministic.py
empulse/metrics/credit_scoring/stochastic.py
empulse/metrics/credit_scoring/__init__.py
empulse/metrics/credit_scoring/_validation.py
empulse/metrics/_loss/loss.pyx
empulse/metrics/_loss/loss.c
empulse/metrics/_loss/__init__.py
empulse/metrics/_loss/loss.py
empulse/metrics/_loss/loss.cpython-311-darwin.so
empulse/metrics/acquisition/deterministic.py
empulse/metrics/acquisition/stochastic.py
empulse/metrics/acquisition/__init__.py
empulse/metrics/acquisition/_validation.py
empulse/metrics/acquisition/cost.py
empulse/metrics/metric/prebuilt_metrics.py
empulse/metrics/metric/metric_strategies.py
empulse/metrics/metric/__init__.py
empulse/metrics/metric/cost_matrix.py
empulse/metrics/metric/metric.py
empulse/metrics/metric/common.py
empulse/metrics/metric/max_profit_metric.py
empulse/metrics/metric/savings_metric.py
empulse/metrics/metric/cost_metric.py
empulse/metrics/churn/deterministic.py
empulse/metrics/churn/stochastic.py
empulse/metrics/churn/__init__.py
empulse/metrics/churn/_validation.py
empulse/metrics/churn/cost.py
empulse/_common/__init__.py
empulse/_common/_parameter.py
empulse/datasets/datasets.py
empulse/datasets/__init__.py
empulse/datasets/descriptions/bankmarketing.rst
empulse/datasets/descriptions/churn_tv_subscriptions.rst
empulse/datasets/descriptions/creditscoring1.rst
empulse/datasets/descriptions/creditscoring2.rst
empulse/datasets/data/bankmarketing.csv.gz
empulse/datasets/data/creditscoring1.csv.gz
empulse/datasets/data/churn_tv_subscriptions.csv.gz
empulse/datasets/data/creditscoring2.csv.gz
empulse/utils/__init__.py
empulse/utils/_sklearn_compat.py
empulse/models/__init__.py
empulse-0.10.4.dist-info/RECORD
empulse-0.10.4.dist-info/WHEEL
empulse-0.10.4.dist-info/top_level.txt
empulse-0.10.4.dist-info/METADATA
empulse-0.10.4.dist-info/licenses/LICENSE
