Metadata-Version: 2.4
Name: empulse
Version: 0.10.4
Summary: Value-driven and cost-sensitive tools for scikit-learn
Author-email: Shimanto Rahman <shimanto.rahman@ugent.be>
Project-URL: documentation, https://empulse.readthedocs.io/en/stable/
Project-URL: repository, https://github.com/ShimantoRahman/empulse
Project-URL: issue-tracker, https://github.com/ShimantoRahman/empulse/issues
Project-URL: changelog, https://empulse.readthedocs.io/en/stable/project/changelog.html
Classifier: Development Status :: 4 - Beta
Classifier: Intended Audience :: Science/Research
Classifier: Intended Audience :: Developers
Classifier: Programming Language :: Python :: 3
Classifier: Programming Language :: Python :: 3 :: Only
Classifier: Programming Language :: Python :: 3.10
Classifier: Programming Language :: Python :: 3.11
Classifier: Programming Language :: Python :: 3.12
Classifier: Programming Language :: Python :: 3.13
Classifier: Operating System :: OS Independent
Classifier: Topic :: Scientific/Engineering
Classifier: Topic :: Scientific/Engineering :: Artificial Intelligence
Classifier: Topic :: Software Development
Classifier: Topic :: Software Development :: Libraries
Classifier: Topic :: Software Development :: Libraries :: Python Modules
Requires-Python: >=3.10
License-File: LICENSE
Requires-Dist: numpy>=1.24.4; python_version < "3.13"
Requires-Dist: numpy>=2.0.0; python_version >= "3.13"
Requires-Dist: scikit-learn>=1.5.2
Requires-Dist: imbalanced-learn>=0.13.0
Requires-Dist: scipy>=1.10.1
Requires-Dist: joblib>=1.3.2
Requires-Dist: pandas>=2.2.0
Requires-Dist: sympy>=1.12.1
Requires-Dist: typing-extensions>=4.0.0
Provides-Extra: optional
Requires-Dist: empulse; extra == "optional"
Requires-Dist: xgboost>=1.7.4; extra == "optional"
Requires-Dist: lightgbm>=4.5.0; extra == "optional"
Requires-Dist: catboost>=1.2.7; python_version < "3.13" and extra == "optional"
Requires-Dist: catboost>=1.2.8; python_version >= "3.13" and extra == "optional"
Dynamic: license-file
